<templateSet group="Balde">
  <template name="app" value="@extends('app')&#10;@section('content')&#10;    $CONTENT$&#10;@stop" description="" toReformat="false" toShortenFQNames="true">
    <variable name="CONTENT" expression="" defaultValue="" alwaysStopAt="true" />
    <context>
      <option name="HTML" value="true" />
      <option name="PHP" value="true" />
    </context>
  </template>
  <template name="bsmedia" value="&lt;div class=&quot;media&quot;&gt;&#10;&lt;div class=&quot;media-left&quot;&gt;&#10;&lt;a href=&quot;#&quot;&gt;&#10;  &lt;img class=&quot;media-object img-circle&quot; alt=&quot;64x64&quot; src=&quot;$IMAGE$&quot; style=&quot;width: 64px; height: 64px;&quot;&gt;&#10;&lt;/a&gt;&#10;&lt;/div&gt;&#10;&lt;div class=&quot;media-body&quot;&gt;&#10;&lt;h4 class=&quot;media-heading&quot;&gt;$NAME$&lt;/h4&gt;&#10;$TITLE$&#10;&lt;/div&gt;&#10;&lt;/div&gt;" description="" toReformat="false" toShortenFQNames="true">
    <variable name="IMAGE" expression="" defaultValue="" alwaysStopAt="true" />
    <variable name="NAME" expression="" defaultValue="" alwaysStopAt="true" />
    <variable name="TITLE" expression="" defaultValue="" alwaysStopAt="true" />
    <context>
      <option name="HTML" value="true" />
      <option name="PHP" value="true" />
    </context>
  </template>
  <template name="bcontainer" value="&lt;div class=&quot;container&quot;&gt;&#10;      &lt;div class=&quot;row&quot;&gt;&#10;        &lt;div class=&quot;col-md-9&quot; role=&quot;main&quot;&gt;&#10;        $CODE$&#10;        &lt;/div&gt;        &#10;      &lt;/div&gt;        &#10;&lt;/div&gt;" description="bs container" toReformat="false" toShortenFQNames="true">
    <variable name="CODE" expression="" defaultValue="" alwaysStopAt="true" />
    <context>
      <option name="HTML" value="true" />
      <option name="PHP" value="true" />
    </context>
  </template>
  <template name="bcss" value=" &lt;link rel=&quot;stylesheet&quot; href=&quot;/css/bootstrap.css&quot;&gt;" description="bs css link" toReformat="false" toShortenFQNames="true">
    <context>
      <option name="HTML" value="true" />
      <option name="PHP" value="true" />
    </context>
  </template>
  <template name="errors" value="@if($errors-&gt;any())&#10;&lt;ul class=&quot;list-group&quot;&gt;&#10;@foreach($errors-&gt;all() as $error)&#10;    &lt;li class=&quot;list-group-item list-group-item-danger&quot;&gt;{ $error }&lt;/li&gt;&#10;@endforeach&#10;&lt;/ul&gt;&#10;@endif" description="" toReformat="false" toShortenFQNames="true">
    <context>
      <option name="HTML" value="true" />
      <option name="PHP" value="true" />
    </context>
  </template>
  <template name="farea" value="&lt;!--- $VALUE$ Field ---&gt;&#10;&lt;div class=&quot;form-group&quot;&gt;&#10;    {!! Form::label('$NAME$', '$VALUE$:') !!}&#10;    {!! Form::textarea('$NAME$', null, ['class' =&gt; 'form-control']) !!}&#10;&lt;/div&gt;" description="" toReformat="false" toShortenFQNames="true">
    <variable name="VALUE" expression="" defaultValue="" alwaysStopAt="true" />
    <variable name="NAME" expression="" defaultValue="" alwaysStopAt="true" />
    <context>
      <option name="HTML" value="true" />
      <option name="PHP" value="true" />
    </context>
  </template>
  <template name="femail" value="&lt;!--- $VALUE$ Field ---&gt;&#10;&lt;div class=&quot;form-group&quot;&gt;&#10;    {!! Form::label('$NAME$', '$VALUE$:') !!}&#10;    {!! Form::email('$NAME$', null, ['class' =&gt; 'form-control']) !!}&#10;&lt;/div&gt;" description="" toReformat="false" toShortenFQNames="true">
    <variable name="VALUE" expression="" defaultValue="" alwaysStopAt="true" />
    <variable name="NAME" expression="" defaultValue="" alwaysStopAt="true" />
    <context>
      <option name="HTML" value="true" />
      <option name="PHP" value="true" />
    </context>
  </template>
  <template name="fpass" value="&lt;!--- $VALUE$ Field ---&gt;&#10;&lt;div class=&quot;form-group&quot;&gt;&#10;    {!! Form::label('$NAME$', '$VALUE$:') !!}&#10;    {!! Form::password('$NAME$', ['class' =&gt; 'form-control']) !!}&#10;&lt;/div&gt;" description="" toReformat="false" toShortenFQNames="true">
    <variable name="VALUE" expression="" defaultValue="" alwaysStopAt="true" />
    <variable name="NAME" expression="" defaultValue="" alwaysStopAt="true" />
    <context>
      <option name="HTML" value="true" />
      <option name="PHP" value="true" />
    </context>
  </template>
  <template name="fsubmit" value="{!! Form::submit('$NAME$',['class'=&gt;'btn btn-primary form-control']) !!}&#10;" description="" toReformat="false" toShortenFQNames="true">
    <variable name="NAME" expression="" defaultValue="" alwaysStopAt="true" />
    <context>
      <option name="HTML" value="true" />
      <option name="PHP" value="true" />
    </context>
  </template>
  <template name="ftext" value="&lt;!--- $VALUE$ Field ---&gt;&#10;&lt;div class=&quot;form-group&quot;&gt;&#10;    {!! Form::label('$NAME$', '$VALUE$:') !!}&#10;    {!! Form::text('$NAME$', null, ['class' =&gt; 'form-control']) !!}&#10;&lt;/div&gt;" description="" toReformat="false" toShortenFQNames="true">
    <variable name="VALUE" expression="" defaultValue="" alwaysStopAt="true" />
    <variable name="NAME" expression="" defaultValue="" alwaysStopAt="true" />
    <context>
      <option name="HTML" value="true" />
      <option name="PHP" value="true" />
    </context>
  </template>
</templateSet>